{"definition":["(of an official) to lose one's job"],"pinyin":["diu1 guan1"],"traditional":["\u4e1f\u5b98"],"rank":-1.0,"normalized_rank":-1.0,"fraction":-1.0,"cumulative_fraction":-1.0,"word":"\u4e22\u5b98","characters":[{"definition":["to lose\/to put aside\/to throw"],"pinyin":["diu1"],"word":"\u4e22"},{"definition":["surname Guan","government official\/governmental\/official\/public\/organ of the body\/CL:\u500b|\u4e2a[ge4]"],"pinyin":["Guan1","guan1"],"word":"\u5b98"}],"containing_words":[],"sentences":[{"english":"You were not selfish or greedy, but your actions have caused you to lose your rank.","chinese":"\u4f60\u4e0d\u81ea\u79c1\u8d2a\u5a6a\uff0c\u4f46\u662f\u4f60\u7684\u6240\u4f5c\u6240\u4e3a\u8db3\u4ee5\u8ba9\u4f60\u4e22\u5b98\u3002"}],"related":[{"definition":["to dismiss from office\/to resign from office"],"pinyin":["ba4 guan1"],"word":"\u7f62\u5b98"},{"definition":["to sack\/to remove from a position\/to depose"],"pinyin":["ge2 zhi2"],"word":"\u9769\u804c"},{"definition":["to commit a crime"],"pinyin":["huo4 zui4"],"word":"\u83b7\u7f6a"},{"definition":["to imprison"],"pinyin":["xia4 yu4"],"word":"\u4e0b\u72f1"},{"definition":["to demote"],"pinyin":["bian3 zhi2"],"word":"\u8d2c\u804c"},{"definition":["to demote (to a lower rank)"],"pinyin":["jiang4 zhi2"],"word":"\u964d\u804c"},{"definition":["demotion to commoner (idiom)"],"pinyin":["xue1 zhi2 wei2 min2"],"word":"\u524a\u804c\u4e3a\u6c11"},{"definition":["to behead"],"pinyin":["sha1 tou2"],"word":"\u6740\u5934"},{"definition":["lit. to lose one's black hat\/to be sacked from an official post"],"pinyin":["diu1 wu1 sha1 mao4"],"word":"\u4e22\u4e4c\u7eb1\u5e3d"},{"definition":["to search a house and confiscate possessions"],"pinyin":["chao1 jia1"],"word":"\u6284\u5bb6"},{"definition":["to execute the whole family and confiscate their property"],"pinyin":["man3 men2 chao1 zhan3"],"word":"\u6ee1\u95e8\u6284\u65a9"},{"definition":["black hat (worn by feudal official)\/fig. official post"],"pinyin":["wu1 sha1 mao4"],"word":"\u4e4c\u7eb1\u5e3d"},{"definition":["to face legal action\/to get sued"],"pinyin":["chi1 guan1 si1"],"word":"\u5403\u5b98\u53f8"},{"definition":["to accuse of misconduct (in official task)\/to impeach"],"pinyin":["tan2 he2"],"word":"\u5f39\u52be"},{"definition":["demotion\/to have one's job cut"],"pinyin":["xue1 zhi2"],"word":"\u524a\u804c"},{"definition":["to punish sb (for a crime)"],"pinyin":["zhi4 zui4"],"word":"\u6cbb\u7f6a"}]}