{"definition":["Asura, malevolent spirits in Indian mythology"],"pinyin":["xiu1 luo2"],"traditional":["\u4fee\u7f85"],"rank":46568.0,"normalized_rank":0.6515467379290082,"fraction":2.0422269997984312e-7,"cumulative_fraction":0.9983664506505684,"word":"\u4fee\u7f57","characters":[{"definition":["dried meat\/private teacher's remuneration\/withered\/variant of \u4fee[xiu1]","surname Xiu","to decorate\/to embellish\/to repair\/to build\/to write\/to cultivate\/to study\/to take (a class)"],"pinyin":["xiu1","Xiu1","xiu1"],"word":"\u4fee"},{"definition":["gauze\/to collect\/to gather\/to catch\/to sift","surname Luo"],"pinyin":["luo2","Luo2"],"word":"\u7f57"}],"containing_words":[{"definition":["Asura, malevolent spirits in Indian mythology"],"pinyin":["A1 xiu1 luo2"],"word":"\u963f\u4fee\u7f57"}],"sentences":[{"english":"The Qin Dynasty holds chin, turning brain to looking at ghost will fix Luo.","chinese":"\u79e6\u671d\u634f\u7740\u4e0b\u5df4\uff0c\u56de\u5934\u770b\u7740\u9b3c\u5c06\u4fee\u7f57\u3002"},{"english":"When Sakka had said this verse, the devas applauded but the asuras were silent.","chinese":"\u5929\u5e1d\u91ca\u5531\u6b64\u5048\u65f6\uff0c\u8bf8\u5929\u6b22\u547c\uff0c\u963f\u4fee\u7f57\u9ed8\u7136\u3002"},{"english":"And I do not think there is anything wrong of Asura.","chinese":"\u6211\u6ca1\u6709\u8ba4\u4e3a\u963f\u4fee\u7f57\u6709\u4ec0\u4e48\u4e0d\u597d\u3002"},{"english":"He is member of the cultural shura of the movement.","chinese":"\u4ed6\u662f\u8fd0\u52a8\u4e2d\u201c\u6587\u5316\u4fee\u7f57\u201d\u7684\u4e00\u5458\u3002"},{"english":"The asuras live on the sea bottom.","chinese":"\u963f\u4fee\u7f57\u4f4f\u5728\u5927\u6d77\u5e95\u3002"},{"english":"Through the autumn fields; his steed, swift as typhoon winds; the arrow, fleeter.","chinese":"\u79cb\u91ce\u4fee\u7f57\u573a\uff0c\u9a90\u9aa5\u5954\u9a70\u795e\u98ce\u52a9\uff0c\u8ffd\u77e2\u4f3c\u98de\u8757\u3002"},{"english":"I think Ashura is a very interesting material.","chinese":"\u6211\u89c9\u5f97\u963f\u4fee\u7f57\u662f\u975e\u5e38\u6709\u610f\u601d\u7684\u7269\u8d28\u3002"},{"english":"Way to fix all the blessing of a day, but without the virtue of nature, natural disposition is aggressive.","chinese":"\u4fee\u7f57\u9053\u4f17\u751f\u6709\u5929\u7684\u798f\uff0c\u4f46\u65e0\u5929\u4eba\u4e4b\u5fb7\uff0c\u751f\u6027\u597d\u6597\u3002"},{"english":"The male Asura is extremely ugly and furious, and they always fight with each other.","chinese":"\u7537\u6027\u963f\u4fee\u7f57\u662f\u975e\u5e38\u4e11\u964b\uff0c\u6124\u6012\uff0c\u4ed6\u4eec\u603b\u662f\u4e92\u76f8\u6597\u4e89\u3002"},{"english":"Asura is one peculiar kind of the six destinies(ways).","chinese":"\u963f\u4fee\u7f57\u662f\u7279\u6709\u7684\u516d\u9053\u4f17\u751f\u4e4b\u4e00\u3002"},{"english":"Now the prayer is that \"we Gods may quell our Asura foemen.\"","chinese":"\u201c\u73b0\u5728\uff0c\u7948\u7977\u7684\u662f\uff0c\u201d\u6211\u4eec\u53ef\u4ee5\u5e73\u606f\u6211\u4eec\u7684\u795e\u963f\u4fee\u7f57\u3002"}],"related":[{"definition":["dark\/hell\/netherworld\/hades"],"pinyin":["you1 ming2"],"word":"\u5e7d\u51a5"},{"definition":["Asura, malevolent spirits in Indian mythology"],"pinyin":["A1 xiu1 luo2"],"word":"\u963f\u4fee\u7f57"},{"definition":["demonic\/devil"],"pinyin":["tian1 mo2"],"word":"\u5929\u9b54"},{"definition":["demon in Buddhism\/poltergeist in temple that plays tricks on monks and has a taste for their food"],"pinyin":["luo2 cha4"],"word":"\u7f57\u5239"},{"definition":["purgatory"],"pinyin":["lian4 yu4"],"word":"\u70bc\u72f1"},{"definition":["evil spirit"],"pinyin":["xie2 mo2"],"word":"\u90aa\u9b54"},{"definition":["the king of hell"],"pinyin":["ming2 wang2"],"word":"\u51a5\u738b"},{"definition":["lit. devils' castle\/place occupied by sinister forces"],"pinyin":["mo2 gong1"],"word":"\u9b54\u5bab"},{"definition":["Nirvana (in Buddhist scripture)\/Lord Brahma (the Hindu Creator)"],"pinyin":["Fan4 tian1"],"word":"\u68b5\u5929"},{"definition":["the Yellow Springs\/the underworld of Chinese mythology\/the equivalent of Hades or Hell"],"pinyin":["Huang2 quan2"],"word":"\u9ec4\u6cc9"},{"definition":["devil king\/evil person"],"pinyin":["mo2 wang2"],"word":"\u9b54\u738b"},{"definition":["treacherous person\/evil spirit"],"pinyin":["gui3 yu4"],"word":"\u9b3c\u872e"},{"definition":["Yama, King of Hell\/translation of Sanskrit: Yama Raja"],"pinyin":["Yan2 luo2"],"word":"\u960e\u7f57"},{"definition":["yaksha (malevolent spirit) (loanword)\/(fig.) ferocious-looking person"],"pinyin":["ye4 cha1"],"word":"\u591c\u53c9"},{"definition":["demon"],"pinyin":["yao1 mo2"],"word":"\u5996\u9b54"},{"definition":["(fig.) specter"],"pinyin":["mo2 ying3"],"word":"\u9b54\u5f71"}]}