{"definition":["to serve as a stopgap\/to make up a shortfall in the number of people"],"pinyin":["cou4 shu4"],"traditional":["\u6e4a\u6578"],"rank":45271.0,"normalized_rank":0.6334000251843354,"fraction":2.3210442671047216e-7,"cumulative_fraction":0.9980834652840792,"word":"\u51d1\u6570","characters":[{"definition":["to gather together, pool or collect\/to happen by chance\/to move close to\/to exploit an opportunity"],"pinyin":["cou4"],"word":"\u51d1"},{"definition":["to count\/to count as\/to regard as\/to enumerate (sb's shortcomings)","number\/figure\/several\/CL:\u500b|\u4e2a[ge4]","frequently\/repeatedly"],"pinyin":["shu3","shu4","shuo4"],"word":"\u6570"}],"containing_words":[],"sentences":[{"english":"He would order 300 musicians at a time to play the Yu for him.","chinese":"\u6709\u4e00\u4e2a\u5357\u90ed\u5148\u751f\uff0c\u672c\u6765\u4e0d\u4f1a\u5439\u7afd\uff0c\u4e5f\u6df7\u5728\u4e2d\u95f4\u51d1\u6570\u3002"},{"english":"If any guest failed at the eleventh hour, Todd was asked to dine.","chinese":"\u8981\u662f\u6709\u4ec0\u4e48\u5ba2\u4eba\u5230\u65f6\u4e0d\u80fd\u6765\uff0c\u6258\u5fb7\u5c31\u7ed9\u8bf7\u6765\u51d1\u6570\u3002"},{"english":"We don't want to bring anyone in just for the sake of bringing.","chinese":"\u6211\u4eec\u4e0d\u4f1a\u4e3a\u4e86\u51d1\u6570\u800c\u968f\u610f\u8d2d\u4e70\u7403\u5458\u3002"},{"english":"Food manufacturers are required to list ingredients in order of quantity after all.","chinese":"\u98df\u54c1\u751f\u4ea7\u5546\u6309\u8981\u6c42\u5217\u51fa\u6210\u5206\u8868\u6bd5\u7adf\u53ea\u4e3a\u4e86\u51d1\u6570\u3002"},{"english":"I'd rather have 24 players, but I don't want to take players on just to make up the numbers.","chinese":"\u6211\u66f4\u503e\u5411\u4e8e\u62e5\u670924\u540d\u9009\u624b\uff0c\u4f46\u662f\u6211\u4e0d\u4f1a\u5355\u7eaf\u7684\u51d1\u6570\u3002"}],"related":[{"definition":["to make up the number (i.e. to fill places up to a given number)\/to serve as stopgap"],"pinyin":["chong1 shu4"],"word":"\u5145\u6570"},{"definition":["to keep up appearances\/to put up a front"],"pinyin":["cheng1 chang3 mian4"],"word":"\u6491\u573a\u9762"},{"definition":["to keep up appearances\/to put up a front"],"pinyin":["cheng1 men2 mian4"],"word":"\u6491\u95e8\u9762"},{"definition":["to buy soy sauce\/it's none of my business (\"I\u2019m just here to buy some soy sauce\")"],"pinyin":["da3 jiang4 you2"],"word":"\u6253\u9171\u6cb9"},{"definition":["lit. to play the yu \u7afd mouth organ to make up numbers (idiom); fig. to make up the numbers with inferior products\/to masquerade as having an ability\/token member of a group"],"pinyin":["lan4 yu2 chong1 shu4"],"word":"\u6ee5\u7afd\u5145\u6570"},{"definition":["to join in the fun\/to get in on the action\/(fig.) to butt in\/to create more trouble"],"pinyin":["cou4 re4 nao5"],"word":"\u51d1\u70ed\u95f9"},{"definition":["not presentable\/shoddy and too embarrassing to show"],"pinyin":["na2 bu4 chu1 shou3"],"word":"\u62ff\u4e0d\u51fa\u624b"},{"definition":["to scrape together enough (people, money etc)"],"pinyin":["cou4 zu2"],"word":"\u51d1\u8db3"},{"definition":["to gather together, pool or collect\/to happen by chance\/to move close to\/to exploit an opportunity"],"pinyin":["cou4"],"word":"\u51d1"},{"definition":["better than nothing (idiom)"],"pinyin":["liao2 sheng4 yu2 wu2"],"word":"\u804a\u80dc\u4e8e\u65e0"},{"definition":["to scare people\/to bluff\/to deceive"],"pinyin":["hu3 ren2"],"word":"\u552c\u4eba"},{"definition":["acceptable\/passable\/justifiable\/(of a course of action) to make sense"],"pinyin":["shuo1 de5 guo4 qu4"],"word":"\u8bf4\u5f97\u8fc7\u53bb"},{"definition":["see \u88dd\u9ede\u9580\u9762|\u88c5\u70b9\u95e8\u9762[zhuang1 dian3 men2 mian4]"],"pinyin":["zhuang1 men2 mian4"],"word":"\u88c5\u95e8\u9762"},{"definition":["to make things up\/to concoct (a story, an excuse etc)"],"pinyin":["hu2 bian1"],"word":"\u80e1\u7f16"},{"definition":["at most\/at best"],"pinyin":["chong1 qi2 liang4"],"word":"\u5145\u5176\u91cf"},{"definition":["lit. to decorate the front of one's store (idiom)\/fig. to embellish (one's CV, etc)\/to keep up appearances\/to put up a front"],"pinyin":["zhuang1 dian3 men2 mian4"],"word":"\u88c5\u70b9\u95e8\u9762"}]}