{"definition":["to send a message"],"pinyin":["fa1 bao4"],"traditional":["\u767c\u5831"],"rank":49599.0,"normalized_rank":0.6939543603878388,"fraction":1.5050293329465206e-7,"cumulative_fraction":0.9989009888970096,"word":"\u53d1\u62a5","characters":[{"definition":["hair\/Taiwan pr. [fa3]","to send out\/to show (one's feeling)\/to issue\/to develop\/to make a bundle of money\/classifier for gunshots (rounds)"],"pinyin":["fa4","fa1"],"word":"\u53d1"},{"definition":["to announce\/to inform\/report\/newspaper\/recompense\/revenge\/CL:\u4efd[fen4],\u5f35|\u5f20[zhang1]"],"pinyin":["bao4"],"word":"\u62a5"}],"containing_words":[{"definition":["sender (of a message)"],"pinyin":["fa1 bao4 ren2"],"word":"\u53d1\u62a5\u4eba"}],"sentences":[{"english":"An apparatus used to transmit radio signals; a transmitter.","chinese":"\u4ed6\u4eec\u60f3\u6cd5\u628a\u5e7f\u64ad\u8bbe\u5907\u6539\u88c5\u6210\u65e0\u7ebf\u7535\u53d1\u62a5\u673a\u3002"},{"english":"You crocheted Star Trek communicators for the whole family.","chinese":"\u4f60\u7ed9\u5168\u5bb6\u6bcf\u4eba\u90fd\u7528\u94a9\u9488\u7f16\u7ec7\u4e86\u4e00\u4e2a\u661f\u7403\u5927\u6218\u53d1\u62a5\u673a\u3002"},{"english":"The sender may use whatever language permitted by the country of destination.","chinese":"\u53d1\u62a5\u4eba\u53ef\u4ee5\u7528\u6536\u62a5\u56fd\u51c6\u7528\u7684\u4efb\u4f55\u8bed\u8a00\u3002"},{"english":"Machine- gun bullets packed up the enemy plane's transmitter.","chinese":"\u673a\u67aa\u5b50\u5f39\u628a\u654c\u673a\u7684\u53d1\u62a5\u673a\u6253\u54d1\u4e86\u3002"},{"english":"As to the receiver and manipulator, they were very simple.","chinese":"\u81f3\u4e8e\u6536\u62a5\u673a\u548c\u53d1\u62a5\u673a\uff0c\u5236\u9020\u8d77\u6765\u975e\u5e38\u7b80\u5355\u3002"},{"english":"An apparatus used to transmit radio signals;","chinese":"\u4ed6\u4eec\u60f3\u6cd5\u628a\u5e7f\u64ad\u8bbe\u5907\u6539\u88c5\u6210\u65e0\u7ebf\u7535\u53d1\u62a5\u673a\u3002"},{"english":"Yes, please . Can you recommend a store where I can buy some gifts for my friends?","chinese":"\u4f60\u80fd\u4e0d\u80fd\u4ecb\u7ecd\u6211\u4e00\u5bb6\u5546\u5e97\uff0c\u6211\u60f3\u4e70\u4e9b\u793c\u53d1\u62a5\u7ed9\u670b\u53cb\u3002"},{"english":"The transmitter, the operator said, has already stood by.","chinese":"\u53d1\u62a5\u5458\u8bf4\uff0c\u53d1\u62a5\u673a\u5df2\u505a\u597d\u4e86\u53d1\u653e\u4fe1\u53f7\u7684\u51c6\u5907\u3002"},{"english":"The transmitter, the operator said, has already stood by.","chinese":"\u53d1\u62a5\u5458\u8bf4\uff0c\u53d1\u62a5\u673a\u5df2\u505a\u597d\u4e86\u53d1\u653e\u4fe1\u53f7\u7684\u51c6\u5907\u3002"}],"related":[{"definition":["telegram\/cable\/telegraph\/CL:\u5c01[feng1],\u4efd[fen4]"],"pinyin":["dian4 bao4"],"word":"\u7535\u62a5"},{"definition":["telegraph operator\/radio operator"],"pinyin":["bao4 wu4 yuan2"],"word":"\u62a5\u52a1\u5458"},{"definition":["coded telegram\/secret telegram"],"pinyin":["mi4 dian4"],"word":"\u5bc6\u7535"},{"definition":["coded telegram\/ciphered cable"],"pinyin":["mi4 ma3 dian4 bao4"],"word":"\u5bc6\u7801\u7535\u62a5"},{"definition":["to send\/to cable (a telegram)"],"pinyin":["pai1 fa1"],"word":"\u62cd\u53d1"},{"definition":["wireless"],"pinyin":["wu2 xian4 dian4"],"word":"\u65e0\u7ebf\u7535"},{"definition":["telegraph receiver"],"pinyin":["shou1 bao4 ji1"],"word":"\u6536\u62a5\u673a"},{"definition":["walkie-talkie\/portable radio transmitter"],"pinyin":["bao4 hua4 ji1"],"word":"\u62a5\u8bdd\u673a"},{"definition":["telegraph"],"pinyin":["dian4 bao4 ji1"],"word":"\u7535\u62a5\u673a"},{"definition":["walkie-talkie"],"pinyin":["bu4 hua4 ji1"],"word":"\u6b65\u8bdd\u673a"},{"definition":["to reply to a telegram\/to wire back"],"pinyin":["hui2 dian4"],"word":"\u56de\u7535"},{"definition":["headquarters\/military command center"],"pinyin":["si1 ling4 bu4"],"word":"\u53f8\u4ee4\u90e8"},{"definition":["recipient (of mail or a message)"],"pinyin":["shou1 bao4 ren2"],"word":"\u6536\u62a5\u4eba"},{"definition":["intelligence office\/intelligence section"],"pinyin":["qing2 bao4 chu4"],"word":"\u60c5\u62a5\u5904"},{"definition":["flag signals (for communicating between ships or army units)\/semaphore"],"pinyin":["qi2 yu3"],"word":"\u65d7\u8bed"},{"definition":["special assignment (military)\/special agent\/operative\/spy"],"pinyin":["te4 wu5"],"word":"\u7279\u52a1"}]}