{"definition":["dialogue\/CL:\u500b|\u4e2a[ge4]"],"pinyin":["dui4 hua4"],"traditional":["\u5c0d\u8a71"],"rank":2338.0,"normalized_rank":0.032711653351615286,"fraction":0.00006346012383755346,"cumulative_fraction":0.7540405399515453,"word":"\u5bf9\u8bdd","characters":[{"definition":["right\/correct\/couple\/pair\/towards\/at\/for\/to face\/opposite\/to treat (sb a certain way)\/to match together\/to adjust\/to fit\/to suit\/to answer\/to reply\/classifier: couple"],"pinyin":["dui4"],"word":"\u5bf9"},{"definition":["dialect\/language\/spoken words\/speech\/talk\/words\/conversation\/what sb said\/CL:\u7a2e|\u79cd[zhong3],\u5e2d[xi2],\u53e5[ju4],\u53e3[kou3],\u756a[fan1]","old variant of \u8a71|\u8bdd[hua4]"],"pinyin":["hua4","hua4"],"word":"\u8bdd"}],"containing_words":[{"definition":["dialog box (computing)"],"pinyin":["dui4 hua4 kuang4"],"word":"\u5bf9\u8bdd\u6846"},{"definition":["bilateral talks"],"pinyin":["liang3 an4 dui4 hua4"],"word":"\u4e24\u5cb8\u5bf9\u8bdd"},{"definition":["conversation class"],"pinyin":["dui4 hua4 ke4"],"word":"\u5bf9\u8bdd\u8bfe"}],"sentences":[{"english":"Further Practice for Pairs \u00b7Add a third speaker and create your own lines.","chinese":"\u52a0\u8fdb\u5708\u5916\u4eba\uff0c\u521b\u4f5c\u4f60\u4eec\u81ea\u5df1\u7684\u5bf9\u8bdd\u3002"},{"english":"LCD screen display, man-machine dialogue, graphic display interface.","chinese":"\u6db2\u6676\u5c4f\u5e55\u663e\u793a\uff0c\u4eba\u673a\u5bf9\u8bdd\uff0c\u56fe\u5f62\u663e\u793a\u754c\u9762\u3002"},{"english":"Use the concept map to promote dialogue and cooperation.","chinese":"\u8fd0\u7528\u6982\u5ff5\u56fe\uff0c\u4fc3\u8fdb\u5bf9\u8bdd\u4e0e\u5408\u4f5c\u3002"},{"english":"'The longer you've known someone, the easier that conversation is, ' Dr. Epperly adds.","chinese":"\u827e\u4f2f\u5229\u533b\u751f\u8bf4\uff0c\u4f60\u8ba4\u8bc6\u75c5\u60a3\u8d8a\u4e45\uff0c\u8fd9\u79cd\u5bf9\u8bdd\u5c31\u8d8a\u5bb9\u6613\u3002"},{"english":"Right-click the project, and launch the properties dialog.","chinese":"\u53f3\u952e\u5355\u51fb\u5de5\u7a0b\uff0c\u542f\u52a8\u5c5e\u6027\u5bf9\u8bdd\u6846\u3002"},{"english":"How ungrateful then that, as the talks limp towards collapse, accusing fingers are being pointed at America.","chinese":"\u968f\u7740\u5bf9\u8bdd\u8d70\u5411\u7834\u88c2\uff0c\u5927\u5bb6\u975e\u5e38\u4e0d\u9886\u60c5\u9762\u5f97\u6307\u8d23\u7f8e\u56fd\u3002"},{"english":"Dear Colleagues, It gives me great pleasure to co-chair the third round of the China-US Economic Dialogue together with Secretary Geithner.","chinese":"\u6211\u5f88\u9ad8\u5174\u4e0e\u76d6\u7279\u7eb3\u8d22\u957f\u5171\u540c\u4e3b\u6301\u7b2c\u4e09\u8f6e\u4e2d\u7f8e\u7ecf\u6d4e\u5bf9\u8bdd\u3002"},{"english":"Then work in pairs, make & act out one.","chinese":"\u5e08\u548c\u4e00\u540d\u751f\u8868\u6f14\u5bf9\u8bdd\u3002"},{"english":"A year after that conversation, Sabine left the relationship.","chinese":"\u5728\u90a3\u6b21\u5bf9\u8bdd\u4e00\u5e74\u4e4b\u540e\uff0cSabine\u79bb\u5f00\u4e86\u3002"},{"english":"We go on and on conversing in our own minds aka thinking.","chinese":"\u6211\u4eec\u548c\u81ea\u5df1\u5bf9\u8bdd\u7684\u65b9\u5f0f\u5c31\u662f\u601d\u8003\u3002"},{"english":"The exchange of words between the man and woman shows a lot about them.","chinese":"\u8fd9\u4f4d\u5973\u58eb\u548c\u8fd9\u4f4d\u7537\u58eb\u95f4\u7684\u5bf9\u8bdd\u8868\u9732\u51fa\u8bb8\u591a\u4fe1\u606f\u3002"},{"english":"Insert Table dialog box opens.","chinese":"\u201c\u63d2\u5165\u8868\u201d\u5bf9\u8bdd\u6846\u968f\u5373\u6253\u5f00\u3002"},{"english":"It was, instead, an example of Chinese stagecraft.","chinese":"\u8fd9\u6b21\u5bf9\u8bdd\u662f\u4e2d\u56fd\u5f0f\u505a\u620f\u7684\u4e00\u4e2a\u5178\u8303\u3002"},{"english":"By definition, a conversation is bi-directional communication.","chinese":"\u987e\u540d\u601d\u4e49\uff0c\u201c\u5bf9\u8bdd\u201d\u5c31\u662f\u4e00\u4e2a\u53cc\u5411\u7684\u6c9f\u901a\u8fc7\u7a0b\u3002"},{"english":"Multi-actor dialog timeline for actor conversations.","chinese":"\u591a\u6f14\u5458\u7684\u6f14\u5458\u4ea4\u8c08\u5bf9\u8bdd\u7684\u65f6\u95f4\u8868\u3002"},{"english":"Typically, that involves retrying for a certain amount of time and then displaying a dialog.","chinese":"\u901a\u5e38\uff0c\u8fd9\u6d89\u53ca\u91cd\u8bd5\u4e00\u6bb5\u65f6\u95f4\u7136\u540e\u663e\u793a\u5bf9\u8bdd\u6846\u3002"}],"related":[{"definition":["to discuss\/to converse\/chat\/discussion"],"pinyin":["jiao1 tan2"],"word":"\u4ea4\u8c08"},{"definition":["to exchange\/exchange\/communication\/interaction\/to have social contact (with sb)"],"pinyin":["jiao1 liu2"],"word":"\u4ea4\u6d41"},{"definition":["to talk with sb (face to face)\/discussion\/talk\/chat"],"pinyin":["dui4 tan2"],"word":"\u5bf9\u8c08"},{"definition":["to talk (with sb)\/to have a conversation\/talk\/conversation\/CL:\u6b21[ci4]"],"pinyin":["tan2 hua4"],"word":"\u8c08\u8bdd"},{"definition":["to interact\/interactive"],"pinyin":["hu4 dong4"],"word":"\u4e92\u52a8"},{"definition":["to visit and discuss\/to interview"],"pinyin":["fang3 tan2"],"word":"\u8bbf\u8c08"},{"definition":["to chat\/to gossip"],"pinyin":["liao2 tian1"],"word":"\u804a\u5929"},{"definition":["lecture\/to make a speech"],"pinyin":["yan3 jiang3"],"word":"\u6f14\u8bb2"},{"definition":["a speech\/to speak\/to talk\/to address\/CL:\u500b|\u4e2a[ge4]"],"pinyin":["jiang3 hua4"],"word":"\u8bb2\u8bdd"},{"definition":["face to face"],"pinyin":["mian4 dui4 mian4"],"word":"\u9762\u5bf9\u9762"},{"definition":["conflict\/to conflict\/clash of opposing forces\/collision (of interests)\/contention"],"pinyin":["chong1 tu1"],"word":"\u51b2\u7a81"},{"definition":["stage monologue\/soliloquy"],"pinyin":["du2 bai2"],"word":"\u72ec\u767d"},{"definition":["to hold a conversation\/to talk over the telephone\/phone call"],"pinyin":["tong1 hua4"],"word":"\u901a\u8bdd"},{"definition":["words\/speech\/utterance\/discourse"],"pinyin":["hua4 yu3"],"word":"\u8bdd\u8bed"},{"definition":["to question\/to quiz\/to grill"],"pinyin":["ti2 wen4"],"word":"\u63d0\u95ee"},{"definition":["words\/speech\/(spoken) language","to speak\/to tell"],"pinyin":["yan2 yu3","yan2 yu5"],"word":"\u8a00\u8bed"}]}