{"definition":["to take one's last breath\/dying"],"pinyin":["qi4 jue2"],"traditional":["\u6c23\u7d55"],"rank":37919.0,"normalized_rank":0.5305360066038923,"fraction":4.677123164656306e-7,"cumulative_fraction":0.9956051432620171,"word":"\u6c14\u7edd","characters":[{"definition":["gas\/air\/smell\/weather\/to make angry\/to annoy\/to get angry\/vital energy\/qi"],"pinyin":["qi4"],"word":"\u6c14"},{"definition":["to cut short\/extinct\/to disappear\/to vanish\/absolutely\/by no means","variant of \u7d55|\u7edd[jue2]"],"pinyin":["jue2","jue2"],"word":"\u7edd"}],"containing_words":[],"sentences":[{"english":"The breath goes now, and some say no;","chinese":"\u53f9\u5176\u6c14\u7edd\u9b42\u79bb\uff0c\u4ea6\u6709\u8bf4\u4e0d\u7136\u3002"},{"english":"How want to get she bears of that carve is also the Han son dent Jie to draw final expiration of does that engrave?","chinese":"\u5982\u4f55\u60f3\u5f97\u5230\u5979\u751f\u4e0b\u7684\u90a3\u523b\u4e5f\u5c31\u662f\u83e1\u513f\u529b\u7aed\u6c14\u7edd\u7684\u90a3\u523b\uff1f"},{"english":"Quality embodies dignity, An outstanding quality will not embrace any sort of mediocrity .","chinese":"\u54c1\u8d28\u4f53\u73b0\u5c0a\u4e25\uff0c\u51fa\u7c7b\u62d4\u8403\u7684\u54c1\u8d28\u6c14\u7edd\u5e73\u5eb8\u3002"},{"english":"By the age of 40, some people are already experiencing breathlessness.","chinese":"\u523040\u5c81\u65f6\uff0c\u6709\u4e9b\u4eba\u5df2\u7ecf\u611f\u5230\u6c14\u7edd\u3002"}],"related":[{"definition":["to meet violent death\/to get killed"],"pinyin":["bi4 ming4"],"word":"\u6bd9\u547d"},{"definition":["to die\/to breathe one's last"],"pinyin":["yan4 qi4"],"word":"\u54bd\u6c14"},{"definition":["to have only a breath of life (idiom)"],"pinyin":["qi4 xi1 yan3 yan3"],"word":"\u6c14\u606f\u5944\u5944"},{"definition":["to stop breathing\/to breathe one's last\/to die\/to cut the gas supply"],"pinyin":["duan4 qi4"],"word":"\u65ad\u6c14"},{"definition":["to die (idiom)\/to breathe one's last\/to give up the ghost"],"pinyin":["yi1 ming4 wu1 hu1"],"word":"\u4e00\u547d\u545c\u547c"},{"definition":["to have lost consciousness"],"pinyin":["ren2 shi4 bu4 zhi1"],"word":"\u4eba\u4e8b\u4e0d\u77e5"},{"definition":["to be decapitated (idiom)"],"pinyin":["shen1 shou3 yi4 chu4"],"word":"\u8eab\u9996\u5f02\u5904"},{"definition":["to faint"],"pinyin":["hun1 jue2"],"word":"\u660f\u53a5"},{"definition":["see \u4e00\u547d\u55da\u547c|\u4e00\u547d\u545c\u547c[yi1 ming4 wu1 hu1]"],"pinyin":["yi1 ming4 gui1 yin1"],"word":"\u4e00\u547d\u5f52\u9634"},{"definition":["to fall dead"],"pinyin":["dao3 bi4"],"word":"\u5012\u6bd9"},{"definition":["see \u4e00\u547d\u55da\u547c|\u4e00\u547d\u545c\u547c[yi1 ming4 wu1 hu1]"],"pinyin":["yi1 ming4 gui1 xi1"],"word":"\u4e00\u547d\u5f52\u897f"},{"definition":["to take a fall"],"pinyin":["zai1 dao3"],"word":"\u683d\u5012"},{"definition":["dead but will not close the eyes (idiom); to die with a remaining grievance"],"pinyin":["si3 bu4 ming2 mu4"],"word":"\u6b7b\u4e0d\u7791\u76ee"},{"definition":["to gush\/to spurt"],"pinyin":["beng4 liu2"],"word":"\u8ff8\u6d41"},{"definition":["to lie down\/to drop dead"],"pinyin":["dao3 wo4"],"word":"\u5012\u5367"},{"definition":["eye socket"],"pinyin":["mu4 zi4"],"word":"\u76ee\u7726"}]}