{"definition":["to draw water"],"pinyin":["ji2 shui3"],"traditional":["\u6c72\u6c34"],"rank":50049.0,"normalized_rank":0.7002504442236929,"fraction":1.4305807432469352e-7,"cumulative_fraction":0.998967032678864,"word":"\u6c72\u6c34","characters":[{"definition":["surname Ji","to draw (water)"],"pinyin":["Ji2","ji2"],"word":"\u6c72"},{"definition":["surname Shui","water\/river\/liquid\/beverage\/additional charges or income\/(of clothes) classifier for number of washes"],"pinyin":["Shui3","shui3"],"word":"\u6c34"}],"containing_words":[],"sentences":[{"english":"Clasping her pitcher to her waist mother went to fetch water from the village nearby.","chinese":"\u5988\u5988\u628a\u5979\u7684\u6c34\u58f6\u5939\u5728\u8170\u95f4\uff0c\u53bb\u90bb\u6751\u6c72\u6c34\u3002"},{"english":"we came across this footbridge where these children were carrying flour.","chinese":"\u6211\u4eec\u5728\u8fc7\u540a\u6865\u65f6\u9047\u5230\u7684\u6c72\u6c34\u7684\u5b69\u5b50\u3002"},{"english":"Clasping her pitcher to her waist mother went to fetch water from the village near by.","chinese":"\u5988\u5988\u628a\u5979\u7684\u6c34\u7f50\u631f\u5728\u8170\u95f4\uff0c\u8d70\u5230\u8fd1\u6751\u6c72\u6c34\u53bb\u4e86\u3002"},{"english":"The daughter of the village blacksmith, who was young and fair , stood at the well , drawing water.","chinese":"\u94c1\u5320\u7684\u90a3\u4e2a\u5e74\u8f7b\u800c\u7f8e\u4e3d\u7684\u5973\u513f\uff0c\u6b63\u7ad9\u5728\u4e95\u8fb9\u6c72\u6c34\u3002"}],"related":[{"definition":["water intake\/to obtain water (from a well etc)"],"pinyin":["qu3 shui3"],"word":"\u53d6\u6c34"},{"definition":["to ladle water\/to scoop up water"],"pinyin":["yao3 shui3"],"word":"\u8200\u6c34"},{"definition":["to draw water\/to splash water"],"pinyin":["da3 shui3"],"word":"\u6253\u6c34"},{"definition":["(water) well"],"pinyin":["shui3 jing3"],"word":"\u6c34\u4e95"},{"definition":["well pulley\/windlass\/potter's wheel"],"pinyin":["lu4 lu5"],"word":"\u8f98\u8f73"},{"definition":["to pilot a ship\/to channel water\/to draw water (for irrigation)"],"pinyin":["yin3 shui3"],"word":"\u5f15\u6c34"},{"definition":["to draw water for irrigation (manually or with a water wheel)"],"pinyin":["hu4 shui3"],"word":"\u623d\u6c34"},{"definition":["mouth of a spring or fountain"],"pinyin":["quan2 yan3"],"word":"\u6cc9\u773c"},{"definition":["to wash (clothes)"],"pinyin":["huan4 xi3"],"word":"\u6d63\u6d17"},{"definition":["water jar"],"pinyin":["shui3 gang1"],"word":"\u6c34\u7f38"},{"definition":["to make tea"],"pinyin":["shao1 cha2"],"word":"\u70e7\u8336"},{"definition":["drought"],"pinyin":["tian1 han4"],"word":"\u5929\u65f1"},{"definition":["well sweep (device for raising and lowering a bucket in a well, using a pivoted pole)"],"pinyin":["jie2 gao1"],"word":"\u6854\u69d4"},{"definition":["canal"],"pinyin":["shui3 qu2"],"word":"\u6c34\u6e20"},{"definition":["to swim"],"pinyin":["qiu2 shui3"],"word":"\u6cc5\u6c34"},{"definition":["pelican\/same as \u9d5c\u9d98|\u9e48\u9e55"],"pinyin":["ti2 hu2"],"word":"\u63d0\u58f6"}]}