{"definition":["slender"],"pinyin":["xi4 chang2"],"traditional":["\u7d30\u9577"],"rank":23907.0,"normalized_rank":0.33448994725280873,"fraction":0.0000016353873537342262,"cumulative_fraction":0.982587110455854,"word":"\u7ec6\u957f","characters":[{"definition":["thin or slender\/finely particulate\/thin and soft\/fine\/delicate\/trifling\/(of a sound) quiet\/frugal"],"pinyin":["xi4"],"word":"\u7ec6"},{"definition":["length\/long\/forever\/always\/constantly","chief\/head\/elder\/to grow\/to develop\/to increase\/to enhance"],"pinyin":["chang2","zhang3"],"word":"\u957f"}],"containing_words":[],"sentences":[{"english":"When the wind blows , the slender tree bends but never breaks.","chinese":"\u8d77\u98ce\u65f6\uff0c\u8fd9\u68f5\u7ec6\u957f\u7684\u6811\u5e38\u5f2f\u66f2\u4f46\u51b3\u4e0d\u4f1a\u65ad\u3002"},{"english":"A slender, elongated, threadlike object or structure.","chinese":"\u7ea4\u7ef4\u4e00\u79cd\u7ec6\u957f\u7684\u7ebf\u72b6\u7269\u4f53\u6216\u7ec4\u7ec7\u3002"},{"english":"Seismosaurus had a long neck, a small head and a long thin tail.","chinese":"\u5730\u9707\u9f99\u957f\u7740\u957f\u8116\u5b50\uff0c\u5c0f\u8111\u888b\uff0c\u4ee5\u53ca\u4e00\u6761\u7ec6\u957f\u7684\u5c3e\u5df4\u3002"},{"english":"The lubricative path is a slightness hole which is oblique to the crank.","chinese":"\u6b64\u6cb9\u9053\u5c5e\u7ec6\u957f\u5b54\uff0c\u4e14\u4e8e\u8f74\u7ebf\u6210\u4e00\u5b9a\u7684\u89d2\u5ea6\u3002"},{"english":"Her long, narrow blue eyes were swimming.","chinese":"\u5979\u90a3\u53cc\u7ec6\u957f\u7684\u84dd\u773c\u775b\u6cea\u6c6a\u6c6a\u7684\u3002"},{"english":"It also appears to have what looks like a string-like arm protruding from its body.","chinese":"\u5b83\u7684\u8eab\u4f53\u5916\u51f8\u51fa\u7684\u80f3\u818a\u50cf\u7ef3\u5b50\u4e00\u6837\u7ec6\u957f\u3002"},{"english":"Large elongated compressed food fish of european atlantic waters.","chinese":"\u6b27\u6d32\u5927\u897f\u6d0b\u6c34\u57df\u8eab\u4f53\u7ec6\u957f\u6241\u5e73\u7684\u98df\u7528\u9c7c\u3002"},{"english":"Changes the nature ensiform leaf blade to be tall and slender. It has the obvious midrib.","chinese":"\u9769\u8d28\u5251\u5f62\u53f6\u7247\u7ec6\u957f\uff0c\u5177\u660e\u663e\u7684\u4e2d\u808b\u3002"},{"english":"The long slender hand dauts wearing a smile photograph piece of cloud and more sees more sorrowful.","chinese":"\u7ec6\u957f\u7684\u624b\u629a\u6478\u7740\u4e91\u542b\u7b11\u7684\u5f20\u7167\u7247\uff0c\u8d8a\u770b\u8d8a\u60b2\u4f24\u3002"},{"english":"Her shadow slenderized under the moonlight.","chinese":"\u5728\u6708\u5149\u4e0b\u5979\u7684\u8eab\u5f71\u53d8\u5f97\u7ec6\u957f\u3002"},{"english":"Any of about 100 species of small, slender freshwater fishes (family Percidae), native to eastern North America.","chinese":"\u9c88\u5f62\u76ee\u9c88\u79d1\u9556\u9c88\u4e9a\u79d1\u7ea6\u4e00\u767e\u79cd\u5c0f\u578b\u7ec6\u957f\u6de1\u6c34\u9c7c\u7684\u7edf\u79f0\u3002"},{"english":"Elongated mostly scaleless marine fishes with large pectoral fins and reduced pelvic fins.","chinese":"\u591a\u6570\u7ec6\u957f\u7684\u65e0\u9cde\u6d77\u6c34\u9c7c\uff0c\u6709\u5927\u7684\u80f8\u548c\u9000\u5316\u7684\u3002"},{"english":"Fruit is medium sized elongated conically shaped with very smooth skin and a high sugar content.","chinese":"\u679c\u5b9e\u4e2d\u578b\u7ec6\u957f\u9525\u5f62\u975e\u5e38\u5149\u6ed1\u76ae\u80a4\u548c\u7cd6\u5206\u8fc7\u9ad8\u3002"},{"english":"Prayer is the slender sinew that moves the muscle of omnipotence.","chinese":"\u7977\u544a\u662f\u7ec6\u957f\u7684\u808c\u8171\u53ef\u4ee5\u7275\u52a8\u65e0\u6240\u4e0d\u80fd\u8005\u7684\u808c\u8089\u3002"},{"english":"Fish with long tubular snout and slim body covered with bony plates.","chinese":"\u957f\u6709\u7ba1\u72b6\u53e3\u9f3b\uff0c\u7ec6\u957f\u7684\u8eab\u4f53\u8868\u9762\u8986\u76d6\u6709\u9aa8\u76d8\u3002"},{"english":"Maggie smiled, her long black hair flowing and almost glowing with sunlight.","chinese":"\u739b\u5409\u53e3\u9732\u5fae\u7b11\uff0c\u5979\u7684\u5934\u53d1\u7ec6\u957f\u800c\u67d4\u987a\uff0c\u4e4c\u9ed1\u800c\u53d1\u4eae\u3002"}],"related":[{"definition":["slender\/lanky\/tall and thin"],"pinyin":["xiu1 chang2"],"word":"\u4fee\u957f"},{"definition":["thick and solid"],"pinyin":["cu1 zhuang4"],"word":"\u7c97\u58ee"},{"definition":["fine\/slim\/tender"],"pinyin":["xian1 xi4"],"word":"\u7ea4\u7ec6"},{"definition":["long and narrow"],"pinyin":["xia2 chang2"],"word":"\u72ed\u957f"},{"definition":["flat\/planar"],"pinyin":["bian3 ping2"],"word":"\u6241\u5e73"},{"definition":["stocky (short and robust)"],"pinyin":["duan3 cu1"],"word":"\u77ed\u7c97"},{"definition":["thick\/bulky\/loud"],"pinyin":["cu1 da4"],"word":"\u7c97\u5927"},{"definition":["slim"],"pinyin":["shou4 chang2"],"word":"\u7626\u957f"},{"definition":["sharp\/keen\/acute\/incisive\/penetrating\/perceptive"],"pinyin":["rui4 li4"],"word":"\u9510\u5229"},{"definition":["remote\/distant\/variant of \u7c97[cu1]","coarse\/rough\/thick (for cylindrical objects)\/unfinished\/vulgar\/rude\/crude","variant of \u7c97[cu1]"],"pinyin":["cu1","cu1","cu1"],"word":"\u7c97"},{"definition":["sharp\/pointed"],"pinyin":["jian1 jian1"],"word":"\u5c16\u5c16"},{"definition":["perfectly straight\/straight as a ramrod\/bolt upright"],"pinyin":["bi3 zhi2"],"word":"\u7b14\u76f4"},{"definition":["spacious\/wide\/lenient"],"pinyin":["kuan1 da4"],"word":"\u5bbd\u5927"},{"definition":["to bend\/to curve around\/curved\/crooked\/to wind\/to warp"],"pinyin":["wan1 qu1"],"word":"\u5f2f\u66f2"},{"definition":["silver (color)"],"pinyin":["yin2 se4"],"word":"\u94f6\u8272"},{"definition":["smooth\/level"],"pinyin":["ping2 zhi2"],"word":"\u5e73\u76f4"}]}