{"definition":["outside horses of a team of 4"],"pinyin":["can1"],"traditional":["\u9a42"],"rank":63438.0,"normalized_rank":0.8875799252864718,"fraction":2.2626532163599485e-8,"cumulative_fraction":0.9999235704939148,"word":"\u9a96","components":{"unicode":"U+9A96","character":"\u9a96","decomposition":"\u2ff0\u9a6c\u53c2","decomposition_definitions":[{"word":"\u2ff0"},{"definition":["horse\/CL:\u5339[pi3]\/horse or cavalry piece in Chinese chess\/knight in Western chess","surname Ma\/abbr. for Malaysia \u99ac\u4f86\u897f\u4e9e|\u9a6c\u6765\u897f\u4e9a[Ma3 lai2 xi1 ya4]"],"pinyin":["ma3","Ma3"],"word":"\u9a6c"},{"definition":["to take part in\/to participate\/to join\/to attend\/to counsel\/unequal\/varied\/irregular\/uneven\/not uniform\/abbr. for \u53c3\u8b70\u9662|\u53c2\u8bae\u9662 Senate, Upper House","variant of \u53c3|\u53c2[shen1]","ginseng\/one of the 28 constellations","old variant of \u53c3|\u53c2[can1]","variant of \u53c3|\u53c2[shen1]"],"pinyin":["can1","shen1","shen1","can1","shen1"],"word":"\u53c2"}]},"containing_words":[],"sentences":[{"english":"Ling Yu Xi Yu after array, Yi Xi right edge left can hurt.","chinese":"\u51cc\u4f59\u9635\u516e\u8e90\u4f59\u884c\uff0c\u5de6\u9a96\u6baa\u516e\u53f3\u5203\u4f24\u3002"}],"related":[{"definition":["bridle\/reins"],"pinyin":["pei4"],"word":"\u8f94"},{"definition":["(literary) good horse (old)"],"pinyin":["su4 shuang1"],"word":"\u9a95\u9aa6"},{"definition":["wild beast\/wild horse\/lion\/trad. form used erroneously for \u8c8c\/simplified form used erroneously for \u72fb","(mythical animal)\/lion"],"pinyin":["ni2","ni2"],"word":"\u730a"},{"definition":["handcart\/emperor's carriage\/to transport by carriage"],"pinyin":["nian3"],"word":"\u8f87"},{"definition":["8 in. length unit of Zhou dynasty"],"pinyin":["zhi3"],"word":"\u54ab"},{"definition":["brown bear"],"pinyin":["pi2"],"word":"\u7f74"},{"definition":["quill"],"pinyin":["he2"],"word":"\u7fee"},{"definition":["leader of herd\/stag"],"pinyin":["zhu3"],"word":"\u9e88"},{"definition":["falcon\/migratory bird"],"pinyin":["hu2"],"word":"\u9e58"},{"definition":["gad-fly"],"pinyin":["fei3"],"word":"\u871a"},{"definition":["turtledove\/(literary) to gather"],"pinyin":["jiu1"],"word":"\u9e20"},{"definition":["to carry on one's back","variant of \u99b1|\u9a6e[tuo2]","load carried by a pack animal"],"pinyin":["tuo2","tuo2","duo4"],"word":"\u9a6e"},{"definition":["ranges of hills"],"pinyin":["lin2"],"word":"\u5d99"},{"definition":["stable\/barn","variant of \u5ec4|\u53a9[jiu4]"],"pinyin":["jiu4","jiu4"],"word":"\u53a9"},{"definition":["team of 4 horses"],"pinyin":["si4"],"word":"\u9a77"},{"definition":["surname Yu","a moment\/little while"],"pinyin":["Yu2","yu2"],"word":"\u81fe"}]}