{"definition":["my presumptuous request (humble expr.); if I may be so bold to ask a favor"],"pinyin":["bu4 qing2 zhi1 qing3"],"simplified":["\u4e0d\u60c5\u4e4b\u8bf7"],"rank":64863.0,"normalized_rank":0.9075175241000096,"fraction":1.6349494208536403e-8,"cumulative_fraction":0.9999513217166384,"word":"\u4e0d\u60c5\u4e4b\u8acb","characters":[{"definition":["(negative prefix)\/not\/no"],"pinyin":["bu4"],"word":"\u4e0d"},{"definition":["feeling\/emotion\/passion\/situation"],"pinyin":["qing2"],"word":"\u60c5"},{"definition":["(possessive particle, literary equivalent of \u7684[de5])\/him\/her\/it"],"pinyin":["zhi1"],"word":"\u4e4b"},{"definition":["to ask\/to invite\/please (do sth)\/to treat (to a meal etc)\/to request"],"pinyin":["qing3"],"word":"\u8acb"}],"containing_words":[],"sentences":[],"related":[]}