{"definition":["icosahedron"],"pinyin":["er4 shi2 mian4 ti3"],"simplified":["\u4e8c\u5341\u9762\u4f53"],"rank":-1.0,"normalized_rank":-1.0,"fraction":-1.0,"cumulative_fraction":-1.0,"word":"\u4e8c\u5341\u9762\u9ad4","characters":[{"definition":["two\/2\/(Beijing dialect) stupid"],"pinyin":["er4"],"word":"\u4e8c"},{"definition":["ten\/10"],"pinyin":["shi2"],"word":"\u5341"},{"definition":["face\/side\/surface\/aspect\/top\/classifier for flat surfaces such as drums, mirrors, flags etc"],"pinyin":["mian4"],"word":"\u9762"},{"definition":["body\/form\/style\/system\/substance\/to experience\/aspect (linguistics)"],"pinyin":["ti3"],"word":"\u9ad4"}],"containing_words":[],"sentences":[],"related":[{"definition":["Ruyuan Yao Autonomous County in Shaoguan \u97f6\u95dc|\u97f6\u5173[Shao2 guan1], Guangdong"],"pinyin":["Ru3 yuan2 Xian4"],"word":"\u4e73\u6e90\u7e23"},{"definition":["oriole\/black-naped oriole (Oriolus chinensis)"],"pinyin":["huang2 peng2"],"word":"\u9ec3\u9d6c"},{"definition":["foreign news media"],"pinyin":["wai4 guo2 mei2 ti3"],"word":"\u5916\u570b\u5a92\u9ad4"},{"definition":["Olympia (Greece)"],"pinyin":["Ao4 lin2 pi3 ya4"],"word":"\u5967\u6797\u5339\u4e9e"},{"definition":["avant-garde"],"pinyin":["xian1 feng1 pai4"],"word":"\u5148\u92d2\u6d3e"},{"definition":["Asian Cup"],"pinyin":["Ya4 zhou1 bei1"],"word":"\u4e9e\u6d32\u76c3"},{"definition":["baker"],"pinyin":["mian4 bao1 shi1 fu4"],"word":"\u9eb5\u5305\u5e2b\u5085"},{"definition":["Marcus Tullius Cicero (106-43 BC), famous Roman politician, orator and philosopher, murdered at the orders of Marc Anthony"],"pinyin":["Xi1 sai1 luo2"],"word":"\u897f\u585e\u7f85"},{"definition":["Wharton (name)"],"pinyin":["Wo4 dun4"],"word":"\u6c83\u9813"},{"definition":["commendation speech\/eulogy\/ode"],"pinyin":["song4 ci2"],"word":"\u980c\u8a5e"},{"definition":["launch pad (for rocket or projectile)"],"pinyin":["fa1 she4 zhan4"],"word":"\u767c\u5c04\u7ad9"},{"definition":["Beijing International Studies University (BISU)"],"pinyin":["Bei3 jing1 Di4 er4 Wai4 guo2 yu3 Xue2 yuan4"],"word":"\u5317\u4eac\u7b2c\u4e8c\u5916\u570b\u8a9e\u5b78\u9662"},{"definition":["maze"],"pinyin":["mi2 zhen4"],"word":"\u8ff7\u9663"},{"definition":["China Youth Daily, www.cyol.net"],"pinyin":["Zhong1 guo2 Qing1 nian2 Bao4"],"word":"\u4e2d\u570b\u9752\u5e74\u5831"},{"definition":["Yellow Pages"],"pinyin":["huang2 ye4"],"word":"\u9ec3\u9801"},{"definition":["poster\/placard\/bill"],"pinyin":["zhao1 tie1"],"word":"\u62db\u8cbc"}]}