{"definition":["sovereign"],"pinyin":["ju4 you3 zhu3 quan2"],"simplified":["\u5177\u6709\u4e3b\u6743"],"rank":-1.0,"normalized_rank":-1.0,"fraction":-1.0,"cumulative_fraction":-1.0,"word":"\u5177\u6709\u4e3b\u6b0a","characters":[{"definition":["tool\/device\/utensil\/equipment\/instrument\/talent\/ability\/to possess\/to have\/to provide\/to furnish\/to state\/classifier for devices, coffins, dead bodies"],"pinyin":["ju4"],"word":"\u5177"},{"definition":["to have\/there is\/there are\/to exist\/to be"],"pinyin":["you3"],"word":"\u6709"},{"definition":["owner\/master\/host\/individual or party concerned\/God\/Lord\/main\/to indicate or signify\/trump card (in card games)"],"pinyin":["zhu3"],"word":"\u4e3b"},{"definition":["authority\/power\/right\/(literary) to weigh\/expedient\/temporary","surname Quan"],"pinyin":["Quan2","quan2"],"word":"\u6b0a"}],"containing_words":[],"sentences":[],"related":[]}