{"definition":["to solicit (guests, clients, passengers etc)\/to importune"],"pinyin":["la1 ke4"],"simplified":["\u62c9\u5ba2"],"rank":16781.0,"normalized_rank":0.23478796188770584,"fraction":0.0000033688716727196703,"cumulative_fraction":0.9656896060176402,"word":"\u62c9\u5ba2","characters":[{"definition":["to pull\/to play (a bowed instrument)\/to drag\/to draw\/to chat"],"pinyin":["la1"],"word":"\u62c9"},{"definition":["customer\/visitor\/guest"],"pinyin":["ke4"],"word":"\u5ba2"}],"containing_words":[],"sentences":[{"english":"Why is it that all these girls are now moving around hustling?","chinese":"\u7232\u4ec0\u9ebc\u73fe\u5728\u5f04\u6210\u4e86\u9019\u4e9b\u5973\u5b69\u5728\u56db\u8655\u2018\u62c9\u5ba2\u2019\uff1f"},{"english":"Look at this little car is not like breaking soliciting, but I do not know him.","chinese":"\u770b\u9019\u5c0f\u7834\u8eca\u4e0d\u50cf\u662f\u62c9\u5ba2\u7684\uff0c\u4f46\u6211\u4e0d\u8a8d\u8b58\u4ed6\u5440\u3002"},{"english":"She was fined for soliciting.","chinese":"\u5979\u56e0\u62c9\u5ba2\u800c\u88ab\u7f70\u6b3e\u3002"},{"english":"A prostitute am soliciting on the road.","chinese":"\u4e00\u540d\u6b63\u5728\u8857\u4e0a\u62c9\u5ba2\u3002"},{"english":"He is a new salesman and he literally pounds the pavement looking for customers.","chinese":"\u4ed6\u662f\u65b0\u4e0a\u5d17\u7684\u63a8\u92b7\u54e1\uff0c\u7232\u4e86\u62c9\u5ba2\u6236\u56db\u8655\u5954\u8d70\u3002"}],"related":[{"definition":["unlicensed or unofficial taxi\/unlicensed motor vehicle"],"pinyin":["hei1 che1"],"word":"\u9ed1\u8eca"},{"definition":["to tout\/to solicit customers"],"pinyin":["la1 sheng1 yi4"],"word":"\u62c9\u751f\u610f"},{"definition":["(northern dialect) to pick up a fare (as a taxi driver)\/to pick up a piece of work (as a courier)"],"pinyin":["la1 huo2"],"word":"\u62c9\u6d3b"},{"definition":["to advertise\/to solicit business"],"pinyin":["zhao1 lan3 sheng1 yi5"],"word":"\u62db\u652c\u751f\u610f"},{"definition":["to thumb a lift\/to hitchhike"],"pinyin":["lan2 che1"],"word":"\u6514\u8eca"},{"definition":["taxi driver"],"pinyin":["chu1 zu1 si1 ji1"],"word":"\u51fa\u79df\u53f8\u6a5f"},{"definition":["motorcycle taxi\/abbr. for \u6469\u6258\u8eca\u7684\u58eb|\u6469\u6258\u8f66\u7684\u58eb[mo2 tuo1 che1 di1 shi4]"],"pinyin":["mo2 di1"],"word":"\u6469\u7684"},{"definition":["to refuse to take a passenger (of taxi)"],"pinyin":["ju4 zai4"],"word":"\u62d2\u8f09"},{"definition":["person who joins with others to reduce costs (carpooling, group buying, sharing an apartment etc)"],"pinyin":["pin1 ke4"],"word":"\u62fc\u5ba2"},{"definition":["to cheat customers\/to overcharge"],"pinyin":["zai3 ke4"],"word":"\u5bb0\u5ba2"},{"definition":["to receive guests\/to receive patrons (of prostitutes)"],"pinyin":["jie1 ke4"],"word":"\u63a5\u5ba2"},{"definition":["chauffeur\/driver\/CL:\u500b|\u4e2a[ge4]"],"pinyin":["si1 ji1"],"word":"\u53f8\u6a5f"},{"definition":["taxi\/(Tw) rental car"],"pinyin":["chu1 zu1 che1"],"word":"\u51fa\u79df\u8eca"},{"definition":["patron of a brothel"],"pinyin":["piao2 ke4"],"word":"\u5ad6\u5ba2"},{"definition":["to take passengers on board"],"pinyin":["zai4 ke4"],"word":"\u8f09\u5ba2"},{"definition":["tuk tuk (three wheeler taxi) (loanword)"],"pinyin":["du1 du1 che1"],"word":"\u561f\u561f\u8eca"}]}