{"definition":["spoilt tea, leftover food (idiom); remains after a meal\/crumbs from the feast"],"pinyin":["can2 cha2 sheng4 fan4"],"simplified":["\u6b8b\u8336\u5269\u996d"],"rank":-1.0,"normalized_rank":-1.0,"fraction":-1.0,"cumulative_fraction":-1.0,"word":"\u6b98\u8336\u5269\u98ef","characters":[{"definition":["to destroy\/to spoil\/to ruin\/to injure\/cruel\/oppressive\/savage\/brutal\/incomplete\/disabled\/to remain\/to survive\/remnant\/surplus"],"pinyin":["can2"],"word":"\u6b98"},{"definition":["tea\/tea plant\/CL:\u676f[bei1],\u58fa|\u58f6[hu2]"],"pinyin":["cha2"],"word":"\u8336"},{"definition":["to remain\/to be left\/to have as remainder"],"pinyin":["sheng4"],"word":"\u5269"},{"definition":["cooked rice\/CL:\u7897[wan3]\/meal\/CL:\u9813|\u987f[dun4]\/(loanword) fan\/devotee"],"pinyin":["fan4"],"word":"\u98ef"}],"containing_words":[],"sentences":[],"related":[]}