{"definition":["reliable\/reasonable\/probable"],"pinyin":["kao4 pu3"],"simplified":["\u9760\u8c31"],"rank":-1.0,"normalized_rank":-1.0,"fraction":-1.0,"cumulative_fraction":-1.0,"word":"\u9760\u8b5c","characters":[{"definition":["to lean against or on\/to stand by the side of\/to come near to\/to depend on\/to trust\/to fuck (vulgar)\/traditional military costume drama where the performers wear armor (old)"],"pinyin":["kao4"],"word":"\u9760"},{"definition":["chart\/list\/table\/register\/score (music)\/spectrum (physics)\/to set to music"],"pinyin":["pu3"],"word":"\u8b5c"}],"containing_words":[],"sentences":[],"related":[{"definition":["mythical horse\/Internet slang for \u4ec0\u9ebc|\u4ec0\u4e48[shen2 me5]"],"pinyin":["shen2 ma3"],"word":"\u795e\u99ac"},{"definition":["original poster (in an online forum)\/landlord of a building (traditional)"],"pinyin":["lou2 zhu3"],"word":"\u6a13\u4e3b"},{"definition":["hey (to call sb)","hey (to express agreement)","hey (to express disagreement)","hey (to express surprise)","sigh (to express regret)"],"pinyin":["ei1","ei2","ei3","ei4","xi1"],"word":"\u8a92"},{"definition":["handsome guy\/lady-killer\/handsome (form of address)"],"pinyin":["shuai4 ge1"],"word":"\u5e25\u54e5"},{"definition":["(question particle for \"yes-no\" questions)","see \u55ce\u5561|\u5417\u5561, morphine"],"pinyin":["ma3","ma5"],"word":"\u55ce"},{"definition":["It is said that ... (at the start of a narrative)\/to discuss\/to recount"],"pinyin":["hua4 shuo1"],"word":"\u8a71\u8aaa"},{"definition":["to seek a marriage partner\/looking for a mate"],"pinyin":["zhao3 dui4 xiang4"],"word":"\u627e\u5c0d\u8c61"},{"definition":["coordinate (geometry)"],"pinyin":["zuo4 biao1"],"word":"\u5750\u6a19"},{"definition":["to come in"],"pinyin":["jin4 lai2"],"word":"\u9032\u4f86"},{"definition":["menfolk (collective term for men of different generations)\/husbands and their fathers etc"],"pinyin":["ye2 men5"],"word":"\u723a\u5011"},{"definition":["to hear (sth said)\/one hears (that)\/hearsay\/listening and speaking"],"pinyin":["ting1 shuo1"],"word":"\u807d\u8aaa"},{"definition":["not bad\/tolerable\/fortunately"],"pinyin":["hai2 hao3"],"word":"\u9084\u597d"},{"definition":["to post (an item on a forum)"],"pinyin":["fa1 tie3"],"word":"\u767c\u5e16"},{"definition":["upstairs\/(Internet slang) previous poster in a forum thread"],"pinyin":["lou2 shang4"],"word":"\u6a13\u4e0a"},{"definition":["as one wishes\/as one pleases\/at random\/negligent\/casual\/wanton"],"pinyin":["sui2 bian4"],"word":"\u96a8\u4fbf"},{"definition":["truth"],"pinyin":["shi2 hua4"],"word":"\u5be6\u8a71"}]}