{"definition":["woodlouse\/pill bug"],"pinyin":["shu3 fu4"],"simplified":["\u9f20\u5987"],"rank":-1.0,"normalized_rank":-1.0,"fraction":-1.0,"cumulative_fraction":-1.0,"word":"\u9f20\u5a66","characters":[{"definition":["rat\/mouse\/CL:\u96bb|\u53ea[zhi1]"],"pinyin":["shu3"],"word":"\u9f20"},{"definition":["woman"],"pinyin":["fu4"],"word":"\u5a66"}],"containing_words":[],"sentences":[{"english":"ObjectiveTo study the analgesic effects of water decoction of Armadillidium vulgare in mice.","chinese":"\u76ee\u7684\u89c0\u5bdf\u9f20\u5a66\u6c34\u714e\u7269\u7684\u93ae\u75db\u4f5c\u7528\u3002"}],"related":[]}